finda/__init__.py
finda/async_ohlcv.py
finda/async_tick.py
finda/cache_manager.py
finda/config.py
finda/live_streamer.py
finda/ohlcv_fetcher.py
finda/schemas.py
finda/tick_fetcher.py
finda-2.0.0.dist-info/METADATA
finda-2.0.0.dist-info/WHEEL
finda-2.0.0.dist-info/top_level.txt
finda-2.0.0.dist-info/RECORD
