Metadata-Version: 2.4
Name: finda
Version: 2.0.0
Summary: Pro-Grade async financial data engine with Parquet caching and multi-provider support
Home-page: https://github.com/kshlgrg/finda
Author: Kushal Garg
Author-email: your.email@example.com
License: MIT
Project-URL: Homepage, https://github.com/kshlgrg/finda
Project-URL: Repository, https://github.com/kshlgrg/finda
Keywords: finance,trading,data-pipeline,async,forex,crypto,stocks,OHLCV,tick-data
Classifier: Development Status :: 4 - Beta
Classifier: Intended Audience :: Financial and Insurance Industry
Classifier: License :: OSI Approved :: MIT License
Classifier: Operating System :: OS Independent
Classifier: Programming Language :: Python :: 3
Classifier: Programming Language :: Python :: 3.9
Classifier: Programming Language :: Python :: 3.10
Classifier: Programming Language :: Python :: 3.11
Classifier: Programming Language :: Python :: 3.12
Classifier: Topic :: Office/Business :: Financial :: Investment
Classifier: Framework :: FastAPI
Classifier: Framework :: AsyncIO
Requires-Python: >=3.7
Requires-Dist: pandas>=1.5.0
Requires-Dist: numpy>=1.21.0
Requires-Dist: pydantic>=2.0.0
Requires-Dist: pydantic-settings>=2.0.0
Requires-Dist: python-dotenv>=1.0.0
Requires-Dist: pyarrow>=10.0.0
Requires-Dist: fastapi>=0.100.0
Requires-Dist: uvicorn>=0.20.0
Requires-Dist: ccxt>=4.0.0
Requires-Dist: dukascopy-python>=0.1.0
Requires-Dist: httpx>=0.24.0
Provides-Extra: alpaca
Requires-Dist: alpaca-py>=0.10.0; extra == "alpaca"
Provides-Extra: all
Requires-Dist: alpaca-py>=0.10.0; extra == "all"
Requires-Dist: aiohttp>=3.8.0; extra == "all"
Dynamic: author-email
Dynamic: home-page
Dynamic: requires-python
